{
  "time": 1710732584433,
  "version": {
    "sideex": [
      4,
      0,
      0
    ],
    "format": [
      2,
      0,
      2
    ]
  },
  "suites": [
    {
      "title": "W106_「銀行優惠」版位確認",
      "description": "",
      "enableOnPlaying": true,
      "cases": [
        {
          "title": "W106_「銀行優惠」版位確認",
          "description": "",
          "enableOnPlaying": true,
          "networkSpeed": 0,
          "records": [
            {
              "name": "open",
              "target": {
                "usedIndex": 0,
                "options": [
                  {
                    "type": "other",
                    "value": "${DOMAIN.WEB}"
                  }
                ],
                "tac": ""
              },
              "value": {
                "usedIndex": 0,
                "options": [
                  {
                    "type": "other",
                    "value": ""
                  }
                ],
                "tac": ""
              },
              "description": "",
              "pwt": {
                "pbw": 0,
                "paw": 0,
                "prw": 0,
                "pdw": 0
              },
              "comment": false,
              "indent": 0
            },
            {
              "name": "verifyPresence",
              "target": {
                "usedIndex": 0,
                "options": [
                  {
                    "type": "other",
                    "value": "//*[@data-regression='index_bankEvent']"
                  }
                ],
                "tac": ""
              },
              "value": {
                "usedIndex": 0,
                "options": [
                  {
                    "type": "other",
                    "value": ""
                  }
                ],
                "tac": ""
              },
              "description": "",
              "pwt": {
                "pbw": 0,
                "paw": 0,
                "prw": 0,
                "pdw": 0
              },
              "comment": false,
              "indent": 0
            },
            {
              "name": "verifyText",
              "target": {
                "usedIndex": 0,
                "options": [
                  {
                    "type": "other",
                    "value": "//*[@data-regression='index_bankEvent']/div/div/div[1]"
                  }
                ],
                "tac": ""
              },
              "value": {
                "usedIndex": 0,
                "options": [
                  {
                    "type": "other",
                    "value": "銀行卡、行動支付\n優惠總覽\n立即查看"
                  }
                ],
                "tac": ""
              },
              "description": "",
              "pwt": {
                "pbw": 0,
                "paw": 0,
                "prw": 0,
                "pdw": 0
              },
              "comment": false,
              "indent": 0
            }
          ]
        }
      ]
    }
  ]
}